examples/__init__.py
examples/autoencoder_example.py
examples/cnn_example.py
examples/simple_dnn.py
sparkflow/HogwildSparkModel.py
sparkflow/RWLock.py
sparkflow/__init__.py
sparkflow/graph_utils.py
sparkflow/ml_util.py
sparkflow/pipeline_util.py
sparkflow/tensorflow_async.py
sparkflow/tensorflow_model_loader.py
sparkflow-0.4.2.dist-info/DESCRIPTION.rst
sparkflow-0.4.2.dist-info/METADATA
sparkflow-0.4.2.dist-info/RECORD
sparkflow-0.4.2.dist-info/WHEEL
sparkflow-0.4.2.dist-info/metadata.json
sparkflow-0.4.2.dist-info/top_level.txt
