Metadata-Version: 2.0
Name: sparkflow
Version: 0.4.2
Summary: Deep learning on Spark with Tensorflow
Home-page: https://github.com/lifeomic/sparkflow
Author: Derek Miller
Author-email: dmmiller612@gmail.com
License: MIT
Download-URL: https://github.com/lifeomic/sparkflow/archive/0.4.2.tar.gz
Keywords: tensorflow,spark,sparkflow,machine learning,lifeomic,deep learning
Platform: UNKNOWN
Requires-Dist: tensorflow
Requires-Dist: flask
Requires-Dist: protobuf
Requires-Dist: requests
